examples/basic_example/example.py
examples/example_reportwriter/example_reportwriter.py
examples/example_scss_preload/example_scss_preload.py
examples/example_with_plot_and_tables/with_plots_and_tables.py
pdf_reports/__init__.py
pdf_reports/pdf_reports.py
pdf_reports/tools.py
pdf_reports/version.py
pdf_reports/css/egf-logo.svg
pdf_reports/css/semantic.min.css
pdf_reports/css/style.css
pdf_reports-0.3.8.dist-info/licenses/LICENCE.txt
tests/test_basics.py
tests/test_tools.py
pdf_reports-0.3.8.dist-info/METADATA
pdf_reports-0.3.8.dist-info/WHEEL
pdf_reports-0.3.8.dist-info/top_level.txt
pdf_reports-0.3.8.dist-info/RECORD
