Metadata-Version: 2.4
Name: pdf_reports
Version: 0.3.8
Summary: Create nice-looking PDF reports from HTML content.
Home-page: https://github.com/Edinburgh-Genome-Foundry/pdf_reports
Author: Zulko
License-Expression: MIT
Project-URL: Homepage, https://github.com/Edinburgh-Genome-Foundry/pdf_reports
Keywords: PDF,report,web,jinja,weasyprint
License-File: LICENCE.txt
Requires-Dist: pypugjs
Requires-Dist: jinja2
Requires-Dist: weasyprint
Requires-Dist: beautifulsoup4
Requires-Dist: pandas
Requires-Dist: Markdown
Requires-Dist: backports.functools-lru-cache
Dynamic: home-page
Dynamic: license-file
